{
  "CHARACTER_LIMIT_MESSAGE": [],
  "logger": [],
  "QuickReply": {
    "CONTENT_TYPES": [],
    "__init__": [
      "self",
      "title",
      "payload",
      "image_url",
      "content_type"
    ],
    "to_dict": [
      "self"
    ]
  },
  "QuickReplies": {
    "__init__": [
      "self",
      "quick_replies"
    ],
    "__bool__": [
      "self"
    ],
    "__nonzero__": [],
    "to_dict": [
      "self"
    ]
  },
  "WEBVIEW_HEIGHT_RATIOS": [],
  "Text": {
    "__init__": [
      "self",
      "text",
      "quick_replies"
    ],
    "to_dict": [
      "self"
    ]
  },
  "DynamicText": {
    "__init__": [
      "self",
      "text",
      "fallback_text",
      "quick_replies"
    ],
    "to_dict": [
      "self"
    ]
  },
  "Button": {
    "BUTTON_TYPES": [],
    "__init__": [
      "self",
      "button_type",
      "title",
      "url",
      "payload",
      "webview_height_ratio",
      "messenger_extensions",
      "fallback_url",
      "share_contents"
    ],
    "to_dict": [
      "self"
    ]
  },
  "Element": {
    "__init__": [
      "self",
      "title",
      "item_url",
      "image_url",
      "subtitle",
      "buttons",
      "quantity",
      "price",
      "currency",
      "default_action"
    ],
    "title": [
      "self",
      "title"
    ],
    "subtitle": [
      "self",
      "subtitle"
    ],
    "to_dict": [
      "self"
    ]
  },
  "Adjustment": {
    "__init__": [
      "self",
      "name",
      "amount"
    ],
    "to_dict": [
      "self"
    ]
  },
  "Address": {
    "__init__": [
      "self",
      "street_1",
      "city",
      "postal_code",
      "state",
      "country",
      "street_2"
    ],
    "to_dict": [
      "self"
    ]
  },
  "Summary": {
    "__init__": [
      "self",
      "total_cost",
      "subtotal",
      "shipping_cost",
      "total_tax"
    ],
    "to_dict": [
      "self"
    ]
  },
  "__version__": [],
  "DEFAULT_API_VERSION": [],
  "MessengerClient": {
    "MESSAGING_TYPES": [],
    "NOTIFICATION_TYPES": [],
    "__init__": [
      "self",
      "page_access_token"
    ],
    "auth_args": [
      "self"
    ],
    "get_user_data": [
      "self",
      "recipient_id",
      "fields",
      "timeout"
    ],
    "send": [
      "self",
      "payload",
      "recipient_id",
      "messaging_type",
      "notification_type",
      "timeout",
      "tag"
    ],
    "send_action": [
      "self",
      "sender_action",
      "recipient_id",
      "timeout"
    ],
    "subscribe_app_to_page": [
      "self",
      "timeout"
    ],
    "set_messenger_profile": [
      "self",
      "data",
      "timeout"
    ],
    "delete_get_started": [
      "self",
      "timeout"
    ],
    "delete_persistent_menu": [
      "self",
      "timeout"
    ],
    "link_account": [
      "self",
      "account_linking_token",
      "timeout"
    ],
    "unlink_account": [
      "self",
      "psid",
      "timeout"
    ],
    "update_whitelisted_domains": [
      "self",
      "domains",
      "timeout"
    ],
    "remove_whitelisted_domains": [
      "self",
      "timeout"
    ],
    "upload_attachment": [
      "self",
      "attachment",
      "timeout"
    ],
    "generate_appsecret_proof": [
      "self"
    ]
  },
  "BaseMessenger": {
    "__metaclass__": [],
    "last_message": [],
    "__init__": [
      "self",
      "page_access_token",
      "app_secret"
    ],
    "account_linking": [
      "self",
      "message"
    ],
    "message": [
      "self",
      "message"
    ],
    "delivery": [
      "self",
      "message"
    ],
    "optin": [
      "self",
      "message"
    ],
    "postback": [
      "self",
      "message"
    ],
    "read": [
      "self",
      "message"
    ],
    "handle": [
      "self",
      "payload"
    ],
    "get_user": [
      "self",
      "fields",
      "timeout"
    ],
    "send": [
      "self",
      "payload",
      "messaging_type",
      "notification_type",
      "timeout",
      "tag"
    ],
    "send_action": [
      "self",
      "sender_action",
      "timeout"
    ],
    "get_user_id": [
      "self"
    ],
    "subscribe_app_to_page": [
      "self",
      "timeout"
    ],
    "set_messenger_profile": [
      "self",
      "data",
      "timeout"
    ],
    "delete_get_started": [
      "self",
      "timeout"
    ],
    "link_account": [
      "self",
      "account_linking_token",
      "timeout"
    ],
    "unlink_account": [
      "self",
      "psid",
      "timeout"
    ],
    "add_whitelisted_domains": [
      "self",
      "domains",
      "timeout"
    ],
    "remove_whitelisted_domains": [
      "self",
      "timeout"
    ],
    "upload_attachment": [
      "self",
      "attachment",
      "timeout"
    ]
  },
  "DEFAULT_LOCALE": [],
  "GreetingText": {
    "__init__": [
      "self",
      "text",
      "locale"
    ],
    "to_dict": [
      "self"
    ]
  },
  "GetStartedButton": {
    "__init__": [
      "self",
      "payload"
    ],
    "to_dict": [
      "self"
    ]
  },
  "PersistentMenuItem": {
    "ITEM_TYPES": [],
    "__init__": [
      "self",
      "item_type",
      "title",
      "nested_items",
      "url",
      "payload",
      "fallback_url",
      "messenger_extensions",
      "webview_share_button",
      "webview_height_ratio"
    ],
    "to_dict": [
      "self"
    ]
  },
  "PersistentMenu": {
    "__init__": [
      "self",
      "menu_items",
      "locale",
      "composer_input_disabled"
    ],
    "to_dict": [
      "self"
    ]
  },
  "MessengerProfile": {
    "__init__": [
      "self",
      "greetings",
      "get_started",
      "persistent_menus"
    ],
    "to_dict": [
      "self"
    ]
  },
  "SenderAction": {
    "SENDER_ACTIONS": [],
    "__init__": [
      "self",
      "sender_action"
    ],
    "to_dict": [
      "self"
    ]
  },
  "BaseTemplate": {
    "TEMPLATE_TYPE": [],
    "__init__": [
      "self",
      "quick_replies"
    ],
    "to_dict": [
      "self"
    ]
  },
  "ElementMixin": {
    "MIN_ELEMENTS": [],
    "MAX_ELEMENTS": [],
    "__init__": [
      "self",
      "elements"
    ],
    "elements": [
      "self",
      "elements"
    ],
    "to_dict": [
      "self"
    ]
  },
  "ButtonMixin": {
    "MIN_BUTTONS": [],
    "MAX_BUTTONS": [],
    "__init__": [
      "self",
      "buttons"
    ],
    "buttons": [
      "self",
      "buttons"
    ],
    "to_dict": [
      "self"
    ]
  },
  "SharableMixin": {
    "__init__": [
      "self",
      "sharable"
    ],
    "to_dict": [
      "self"
    ]
  },
  "GenericTemplate": {
    "TEMPLATE_TYPE": [],
    "MIN_ELEMENTS": [],
    "MAX_ELEMENTS": [],
    "__init__": [
      "self",
      "elements",
      "quick_replies",
      "image_aspect_ratio"
    ],
    "to_dict": [
      "self"
    ]
  },
  "MediaTemplate": {
    "TEMPLATE_TYPE": [],
    "VALID_MEDIA_TYPES": [],
    "__init__": [
      "self",
      "media",
      "buttons"
    ],
    "to_dict": [
      "self"
    ]
  },
  "ButtonTemplate": {
    "TEMPLATE_TYPE": [],
    "MIN_BUTTONS": [],
    "MAX_BUTTONS": [],
    "__init__": [
      "self",
      "text",
      "buttons",
      "quick_replies"
    ],
    "to_dict": [
      "self"
    ]
  },
  "ListTemplate": {
    "TEMPLATE_TYPE": [],
    "MIN_BUTTONS": [],
    "MAX_BUTTONS": [],
    "MIN_ELEMENTS": [],
    "MAX_ELEMENTS": [],
    "__init__": [
      "self",
      "elements",
      "top_element_style"
    ],
    "to_dict": [
      "self"
    ]
  },
  "ReceiptTemplate": {
    "TEMPLATE_TYPE": [],
    "MIN_ELEMENTS": [],
    "MAX_ELEMENTS": [],
    "__init__": [
      "self",
      "recipient_name",
      "order_number",
      "currency",
      "payment_method",
      "elements",
      "summary",
      "order_url",
      "timestamp",
      "address",
      "adjustments",
      "quick_replies"
    ],
    "to_dict": [
      "self"
    ]
  },
  "BaseAttachment": {
    "__init__": [
      "self",
      "attachment_type",
      "url",
      "is_reusable",
      "quick_replies",
      "attachment_id"
    ],
    "to_dict": [
      "self"
    ]
  },
  "Image": {
    "__init__": [
      "self",
      "url",
      "is_reusable",
      "quick_replies",
      "attachment_id"
    ]
  },
  "Audio": {
    "__init__": [
      "self",
      "url",
      "is_reusable",
      "quick_replies",
      "attachment_id"
    ]
  },
  "Video": {
    "__init__": [
      "self",
      "url",
      "is_reusable",
      "quick_replies",
      "attachment_id"
    ]
  },
  "File": {
    "__init__": [
      "self",
      "url",
      "is_reusable",
      "quick_replies",
      "attachment_id"
    ]
  }
}