{
  "CallGraphGenerator": {
    "__init__": [
      "self",
      "entry_points",
      "package",
      "max_iter",
      "operation"
    ],
    "setUp": [
      "self"
    ],
    "extract_state": [
      "self"
    ],
    "reset_counters": [
      "self"
    ],
    "has_converged": [
      "self"
    ],
    "remove_import_hooks": [
      "self"
    ],
    "tearDown": [
      "self"
    ],
    "_get_mod_name": [
      "self",
      "entry",
      "pkg"
    ],
    "do_pass": [
      "self",
      "cls",
      "install_hooks"
    ],
    "analyze": [
      "self"
    ],
    "output": [
      "self"
    ],
    "output_key_errs": [
      "self"
    ],
    "output_edges": [
      "self"
    ],
    "_generate_mods": [
      "self",
      "mods"
    ],
    "output_internal_mods": [
      "self"
    ],
    "output_external_mods": [
      "self"
    ],
    "output_functions": [
      "self"
    ],
    "output_classes": [
      "self"
    ],
    "get_as_graph": [
      "self"
    ]
  },
  "main": [],
  "TestBase": {},
  "CallGraphTest": {
    "setUp": [
      "self"
    ],
    "tearDown": [
      "self"
    ],
    "test_setup": [
      "self"
    ],
    "test_add_node": [
      "self"
    ],
    "test_add_edge": [
      "self"
    ]
  },
  "FastenFormatTest": {
    "FORGE": [],
    "PRODUCT": [],
    "PACKAGE": [],
    "VERSION": [],
    "TIMESTAMP": [],
    "setUp": [
      "self"
    ],
    "get_formatter": [
      "self"
    ],
    "test_cli_args": [
      "self"
    ],
    "test_uri": [
      "self"
    ],
    "_get_internal_mods": [
      "self"
    ],
    "_get_external_mods": [
      "self"
    ],
    "_get_classes": [
      "self"
    ],
    "test_internal_modules": [
      "self"
    ],
    "test_external_modules": [
      "self"
    ],
    "test_hiearchy": [
      "self"
    ]
  },
  "ScopeManagerTest": {
    "test_handle_module": [
      "self"
    ],
    "test_handle_assign": [
      "self"
    ],
    "test_get_def": [
      "self"
    ],
    "test_get_scope": [
      "self"
    ]
  },
  "ScopeItemTest": {
    "test_setup": [
      "self"
    ],
    "test_get_ns": [
      "self"
    ],
    "test_defs": [
      "self"
    ]
  },
  "DefinitionManagerTest": {
    "test_create": [
      "self"
    ],
    "test_assign": [
      "self"
    ],
    "test_handle_function_def": [
      "self"
    ]
  },
  "ImportsTest": {
    "test_create_node": [
      "self"
    ],
    "test_set_filepath": [
      "self"
    ],
    "test_create_edge": [
      "self"
    ],
    "test_hooks": [
      "self"
    ],
    "test_custom_loader": [
      "self"
    ],
    "test_handle_import_level": [
      "self"
    ],
    "test_handle_import": [
      "self"
    ]
  },
  "PointerTest": {
    "test_merge": [
      "self"
    ],
    "test_literal_pointer": [
      "self"
    ],
    "test_name_pointer": [
      "self"
    ],
    "test_name_pointer_merge": [
      "self"
    ]
  },
  "ProcessingBase": {
    "__init__": [
      "self",
      "filename",
      "modname",
      "modules_analyzed"
    ],
    "get_modules_analyzed": [
      "self"
    ],
    "merge_modules_analyzed": [
      "self",
      "analyzed"
    ],
    "current_ns": [
      "self"
    ],
    "current_method": [
      "self"
    ],
    "visit_Module": [
      "self",
      "node"
    ],
    "visit_FunctionDef": [
      "self",
      "node"
    ],
    "visit_Lambda": [
      "self",
      "node",
      "lambda_name"
    ],
    "visit_For": [
      "self",
      "node"
    ],
    "visit_Dict": [
      "self",
      "node"
    ],
    "visit_List": [
      "self",
      "node"
    ],
    "visit_BinOp": [
      "self",
      "node"
    ],
    "visit_ClassDef": [
      "self",
      "node"
    ],
    "visit_Tuple": [
      "self",
      "node"
    ],
    "_handle_assign": [
      "self",
      "targetns",
      "decoded"
    ],
    "_visit_return": [
      "self",
      "node"
    ],
    "_get_target_ns": [
      "self",
      "target"
    ],
    "_visit_assign": [
      "self",
      "value",
      "targets"
    ],
    "decode_node": [
      "self",
      "node"
    ],
    "_is_literal": [
      "self",
      "item"
    ],
    "_retrieve_base_names": [
      "self",
      "node"
    ],
    "_retrieve_parent_names": [
      "self",
      "node"
    ],
    "_retrieve_attribute_names": [
      "self",
      "node"
    ],
    "iterate_call_args": [
      "self",
      "defi",
      "node"
    ],
    "retrieve_subscript_names": [
      "self",
      "node"
    ],
    "retrieve_call_names": [
      "self",
      "node"
    ],
    "analyze_submodules": [
      "self",
      "cls"
    ],
    "analyze_submodule": [
      "self",
      "cls",
      "imp"
    ],
    "find_cls_fun_ns": [
      "self",
      "cls_name",
      "fn"
    ],
    "add_ext_mod_node": [
      "self",
      "name"
    ]
  },
  "KeyErrProcessor": {
    "__init__": [
      "self",
      "filename",
      "modname",
      "import_manager",
      "scope_manager",
      "def_manager",
      "class_manager",
      "key_errs",
      "modules_analyzed"
    ],
    "visit_Subscript": [
      "self",
      "node"
    ],
    "is_subscriptable": [
      "self",
      "name"
    ],
    "analyze_submodules": [
      "self"
    ],
    "analyze": [
      "self"
    ],
    "visit_Lambda": [
      "self",
      "node"
    ]
  },
  "PreProcessor": {
    "__init__": [
      "self",
      "filename",
      "modname",
      "import_manager",
      "scope_manager",
      "def_manager",
      "class_manager",
      "module_manager",
      "modules_analyzed"
    ],
    "_get_fun_defaults": [
      "self",
      "node"
    ],
    "analyze_submodule": [
      "self",
      "modname"
    ],
    "visit_Module": [
      "self",
      "node"
    ],
    "visit_Import": [
      "self",
      "node",
      "prefix",
      "level"
    ],
    "visit_ImportFrom": [
      "self",
      "node"
    ],
    "_get_last_line": [
      "self",
      "node"
    ],
    "_handle_function_def": [
      "self",
      "node",
      "fn_name"
    ],
    "visit_AsyncFunctionDef": [
      "self",
      "node"
    ],
    "visit_FunctionDef": [
      "self",
      "node"
    ],
    "visit_For": [
      "self",
      "node"
    ],
    "visit_Assign": [
      "self",
      "node"
    ],
    "visit_Return": [
      "self",
      "node"
    ],
    "visit_Yield": [
      "self",
      "node"
    ],
    "visit_Call": [
      "self",
      "node"
    ],
    "visit_Lambda": [
      "self",
      "node"
    ],
    "visit_ClassDef": [
      "self",
      "node"
    ],
    "analyze": [
      "self"
    ]
  },
  "PostProcessor": {
    "__init__": [
      "self",
      "input_file",
      "modname",
      "import_manager",
      "scope_manager",
      "def_manager",
      "class_manager",
      "module_manager",
      "modules_analyzed"
    ],
    "visit_Lambda": [
      "self",
      "node"
    ],
    "visit_Call": [
      "self",
      "node"
    ],
    "visit_Assign": [
      "self",
      "node"
    ],
    "visit_For": [
      "self",
      "node"
    ],
    "visit_Return": [
      "self",
      "node"
    ],
    "visit_Yield": [
      "self",
      "node"
    ],
    "visit_AsyncFunctionDef": [
      "self",
      "node"
    ],
    "visit_FunctionDef": [
      "self",
      "node"
    ],
    "visit_ClassDef": [
      "self",
      "node"
    ],
    "visit_List": [
      "self",
      "node"
    ],
    "visit_Dict": [
      "self",
      "node"
    ],
    "update_parent_classes": [
      "self",
      "defi"
    ],
    "analyze_submodules": [
      "self"
    ],
    "analyze": [
      "self"
    ]
  },
  "CallGraphProcessor": {
    "__init__": [
      "self",
      "filename",
      "modname",
      "import_manager",
      "scope_manager",
      "def_manager",
      "class_manager",
      "module_manager",
      "call_graph",
      "modules_analyzed"
    ],
    "visit_Module": [
      "self",
      "node"
    ],
    "visit_For": [
      "self",
      "node"
    ],
    "visit_Lambda": [
      "self",
      "node"
    ],
    "visit_Raise": [
      "self",
      "node"
    ],
    "visit_AsyncFunctionDef": [
      "self",
      "node"
    ],
    "visit_FunctionDef": [
      "self",
      "node"
    ],
    "visit_Call": [
      "self",
      "node"
    ],
    "analyze_submodules": [
      "self"
    ],
    "analyze": [
      "self"
    ],
    "get_all_reachable_functions": [
      "self"
    ],
    "has_ext_parent": [
      "self",
      "node"
    ],
    "get_full_attr_names": [
      "self",
      "node"
    ],
    "is_builtin": [
      "self",
      "name"
    ]
  },
  "ClassManager": {
    "__init__": [
      "self"
    ],
    "get": [
      "self",
      "name"
    ],
    "create": [
      "self",
      "name",
      "module"
    ],
    "get_classes": [
      "self"
    ]
  },
  "ClassNode": {
    "__init__": [
      "self",
      "ns",
      "module"
    ],
    "add_parent": [
      "self",
      "parent"
    ],
    "fix_mro": [
      "self"
    ],
    "get_mro": [
      "self"
    ],
    "get_module": [
      "self"
    ],
    "compute_mro": [
      "self"
    ],
    "clear_mro": [
      "self"
    ]
  },
  "DefinitionManager": {
    "__init__": [
      "self"
    ],
    "create": [
      "self",
      "ns",
      "def_type"
    ],
    "assign": [
      "self",
      "ns",
      "defi"
    ],
    "get": [
      "self",
      "ns"
    ],
    "get_defs": [
      "self"
    ],
    "handle_function_def": [
      "self",
      "parent_ns",
      "fn_name"
    ],
    "handle_class_def": [
      "self",
      "parent_ns",
      "cls_name"
    ],
    "transitive_closure": [
      "self"
    ],
    "complete_definitions": [
      "self"
    ]
  },
  "Definition": {
    "types": [],
    "__init__": [
      "self",
      "fullns",
      "def_type"
    ],
    "get_type": [
      "self"
    ],
    "is_function_def": [
      "self"
    ],
    "is_ext_def": [
      "self"
    ],
    "is_callable": [
      "self"
    ],
    "get_lit_pointer": [
      "self"
    ],
    "get_name_pointer": [
      "self"
    ],
    "get_name": [
      "self"
    ],
    "get_ns": [
      "self"
    ],
    "merge": [
      "self",
      "to_merge"
    ]
  },
  "DefinitionError": {},
  "CallGraph": {
    "__init__": [
      "self"
    ],
    "add_node": [
      "self",
      "name",
      "modname"
    ],
    "add_edge": [
      "self",
      "src",
      "dest"
    ],
    "get": [
      "self"
    ],
    "get_edges": [
      "self"
    ],
    "get_modules": [
      "self"
    ]
  },
  "CallGraphError": {},
  "KeyErrors": {
    "__init__": [
      "self"
    ],
    "add": [
      "self",
      "filename",
      "lineno",
      "namespace",
      "key"
    ],
    "get": [
      "self"
    ]
  },
  "get_custom_loader": [
    "ig_obj"
  ],
  "ImportManager": {
    "__init__": [
      "self"
    ],
    "set_pkg": [
      "self",
      "input_pkg"
    ],
    "get_mod_dir": [
      "self"
    ],
    "get_node": [
      "self",
      "name"
    ],
    "create_node": [
      "self",
      "name"
    ],
    "create_edge": [
      "self",
      "dest"
    ],
    "_clear_caches": [
      "self"
    ],
    "_get_module_path": [
      "self"
    ],
    "set_current_mod": [
      "self",
      "name",
      "fname"
    ],
    "get_filepath": [
      "self",
      "modname"
    ],
    "set_filepath": [
      "self",
      "node_name",
      "filename"
    ],
    "get_imports": [
      "self",
      "modname"
    ],
    "_is_init_file": [
      "self"
    ],
    "_handle_import_level": [
      "self",
      "name",
      "level"
    ],
    "_do_import": [
      "self",
      "mod_name",
      "package"
    ],
    "handle_import": [
      "self",
      "name",
      "level"
    ],
    "get_import_graph": [
      "self"
    ],
    "install_hooks": [
      "self"
    ],
    "remove_hooks": [
      "self"
    ]
  },
  "ImportManagerError": {},
  "Pointer": {
    "__init__": [
      "self"
    ],
    "add": [
      "self",
      "item"
    ],
    "add_set": [
      "self",
      "s"
    ],
    "get": [
      "self"
    ],
    "merge": [
      "self",
      "pointer"
    ]
  },
  "LiteralPointer": {
    "STR_LIT": [],
    "INT_LIT": [],
    "UNK_LIT": [],
    "add": [
      "self",
      "item"
    ]
  },
  "NamePointer": {
    "__init__": [
      "self"
    ],
    "_sanitize_pos": [
      "self",
      "pos"
    ],
    "get_or_create": [
      "self",
      "name"
    ],
    "add_arg": [
      "self",
      "name",
      "item"
    ],
    "add_lit_arg": [
      "self",
      "name",
      "item"
    ],
    "add_pos_arg": [
      "self",
      "pos",
      "name",
      "item"
    ],
    "add_name_arg": [
      "self",
      "name",
      "item"
    ],
    "add_pos_lit_arg": [
      "self",
      "pos",
      "name",
      "item"
    ],
    "get_pos_arg": [
      "self",
      "pos"
    ],
    "get_arg": [
      "self",
      "name"
    ],
    "get_args": [
      "self"
    ],
    "get_pos_args": [
      "self"
    ],
    "get_pos_of_name": [
      "self",
      "name"
    ],
    "get_pos_names": [
      "self"
    ],
    "merge": [
      "self",
      "pointer"
    ]
  },
  "PointerError": {},
  "ScopeManager": {
    "__init__": [
      "self"
    ],
    "handle_module": [
      "self",
      "modulename",
      "filename",
      "contents"
    ],
    "handle_assign": [
      "self",
      "ns",
      "target",
      "defi"
    ],
    "get_def": [
      "self",
      "current_ns",
      "var_name"
    ],
    "get_scope": [
      "self",
      "namespace"
    ],
    "create_scope": [
      "self",
      "namespace",
      "parent"
    ],
    "get_scopes": [
      "self"
    ]
  },
  "ScopeItem": {
    "__init__": [
      "self",
      "fullns",
      "parent"
    ],
    "get_ns": [
      "self"
    ],
    "get_defs": [
      "self"
    ],
    "get_def": [
      "self",
      "name"
    ],
    "get_lambda_counter": [
      "self"
    ],
    "get_dict_counter": [
      "self"
    ],
    "get_list_counter": [
      "self"
    ],
    "inc_lambda_counter": [
      "self",
      "val"
    ],
    "inc_dict_counter": [
      "self",
      "val"
    ],
    "inc_list_counter": [
      "self",
      "val"
    ],
    "reset_counters": [
      "self"
    ],
    "add_def": [
      "self",
      "name",
      "defi"
    ],
    "merge_def": [
      "self",
      "name",
      "to_merge"
    ]
  },
  "ScopeError": {},
  "ModuleManager": {
    "__init__": [
      "self"
    ],
    "create": [
      "self",
      "name",
      "fname",
      "external"
    ],
    "get": [
      "self",
      "name"
    ],
    "get_internal_modules": [
      "self"
    ],
    "get_external_modules": [
      "self"
    ]
  },
  "Module": {
    "__init__": [
      "self",
      "name",
      "filename"
    ],
    "get_name": [
      "self"
    ],
    "get_filename": [
      "self"
    ],
    "get_methods": [
      "self"
    ],
    "add_method": [
      "self",
      "method",
      "first",
      "last"
    ]
  },
  "BaseFormatter": {
    "generate": [
      "self"
    ]
  },
  "Simple": {
    "__init__": [
      "self",
      "cg_generator"
    ],
    "generate": [
      "self"
    ]
  },
  "AsGraph": {
    "__init__": [
      "self",
      "cg_generator"
    ],
    "generate": [
      "self"
    ]
  },
  "Fasten": {
    "__init__": [
      "self",
      "cg_generator",
      "package",
      "product",
      "forge",
      "version",
      "timestamp"
    ],
    "get_unique_and_increment": [
      "self"
    ],
    "to_uri": [
      "self",
      "modname",
      "name"
    ],
    "to_external_uri": [
      "self",
      "modname",
      "name"
    ],
    "find_dependencies": [
      "self",
      "package_path"
    ],
    "get_internal_modules": [
      "self"
    ],
    "add_superclasses": [
      "self",
      "mods"
    ],
    "create_namespaces_map": [
      "self"
    ],
    "get_external_modules": [
      "self"
    ],
    "get_graph": [
      "self"
    ],
    "generate": [
      "self"
    ]
  },
  "get_lambda_name": [
    "counter"
  ],
  "get_dict_name": [
    "counter"
  ],
  "get_list_name": [
    "counter"
  ],
  "get_int_name": [
    "counter"
  ],
  "join_ns": [],
  "to_mod_name": [
    "name",
    "package"
  ],
  "RETURN_NAME": [],
  "LAMBDA_NAME": [],
  "BUILTIN_NAME": [],
  "EXT_NAME": [],
  "FUN_DEF": [],
  "NAME_DEF": [],
  "MOD_DEF": [],
  "CLS_DEF": [],
  "EXT_DEF": [],
  "OBJECT_BASE": [],
  "CLS_INIT": [],
  "ITER_METHOD": [],
  "NEXT_METHOD": [],
  "STATIC_METHOD": [],
  "INVALID_NAME": [],
  "CALL_GRAPH_OP": [],
  "KEY_ERR_OP": []
}