{
  "__author__": [],
  "__version__": [],
  "PY2": [],
  "PY3": [],
  "PY34": [],
  "_add_doc": [
    "func",
    "doc"
  ],
  "_import_module": [
    "name"
  ],
  "_LazyDescr": {
    "__init__": [
      "self",
      "name"
    ],
    "__get__": [
      "self",
      "obj",
      "tp"
    ]
  },
  "MovedModule": {
    "__init__": [
      "self",
      "name",
      "old",
      "new"
    ],
    "_resolve": [
      "self"
    ],
    "__getattr__": [
      "self",
      "attr"
    ]
  },
  "_LazyModule": {
    "__init__": [
      "self",
      "name"
    ],
    "__dir__": [
      "self"
    ],
    "_moved_attributes": []
  },
  "MovedAttribute": {
    "__init__": [
      "self",
      "name",
      "old_mod",
      "new_mod",
      "old_attr",
      "new_attr"
    ],
    "_resolve": [
      "self"
    ]
  },
  "_SixMetaPathImporter": {
    "__init__": [
      "self",
      "six_module_name"
    ],
    "_add_module": [
      "self",
      "mod"
    ],
    "_get_module": [
      "self",
      "fullname"
    ],
    "find_module": [
      "self",
      "fullname",
      "path"
    ],
    "__get_module": [
      "self",
      "fullname"
    ],
    "load_module": [
      "self",
      "fullname"
    ],
    "is_package": [
      "self",
      "fullname"
    ],
    "get_code": [
      "self",
      "fullname"
    ],
    "get_source": []
  },
  "_importer": [],
  "_MovedItems": {
    "__path__": []
  },
  "_moved_attributes": [],
  "moves": [],
  "Module_six_moves_urllib_parse": {},
  "_urllib_parse_moved_attributes": [],
  "Module_six_moves_urllib_error": {},
  "_urllib_error_moved_attributes": [],
  "Module_six_moves_urllib_request": {},
  "_urllib_request_moved_attributes": [],
  "Module_six_moves_urllib_response": {},
  "_urllib_response_moved_attributes": [],
  "Module_six_moves_urllib_robotparser": {},
  "_urllib_robotparser_moved_attributes": [],
  "Module_six_moves_urllib": {
    "__path__": [],
    "parse": [],
    "error": [],
    "request": [],
    "response": [],
    "robotparser": [],
    "__dir__": [
      "self"
    ]
  },
  "add_move": [
    "move"
  ],
  "remove_move": [
    "name"
  ],
  "next": [],
  "get_method_function": [],
  "get_method_self": [],
  "get_function_closure": [],
  "get_function_code": [],
  "get_function_defaults": [],
  "get_function_globals": [],
  "assertCountEqual": [
    "self"
  ],
  "assertRaisesRegex": [
    "self"
  ],
  "assertRegex": [
    "self"
  ],
  "assertNotRegex": [
    "self"
  ],
  "print_": [],
  "with_metaclass": [
    "meta"
  ],
  "add_metaclass": [
    "metaclass"
  ],
  "ensure_binary": [
    "s",
    "encoding",
    "errors"
  ],
  "ensure_str": [
    "s",
    "encoding",
    "errors"
  ],
  "ensure_text": [
    "s",
    "encoding",
    "errors"
  ],
  "python_2_unicode_compatible": [
    "klass"
  ],
  "__path__": [],
  "__package__": [],
  "deprecated": [
    "message"
  ],
  "logger": [],
  "__all__": [],
  "SENSITIVE_KEYS": [],
  "DEFAULT_HOST": [],
  "DEFAULT_PORT": [],
  "DEFAULT_SCHEME": [],
  "_log_duration": [
    "f"
  ],
  "mask_sensitive_data": [
    "data"
  ],
  "_parse_cookies": [
    "cookie_str",
    "dictionary"
  ],
  "_make_cookie_header": [
    "cookies"
  ],
  "_NoAuthenticationToken": {},
  "UrlEncoded": {
    "__new__": [
      "self",
      "val",
      "skip_encode",
      "encode_slash"
    ],
    "__add__": [
      "self",
      "other"
    ],
    "__radd__": [
      "self",
      "other"
    ],
    "__mod__": [
      "self",
      "fields"
    ],
    "__repr__": [
      "self"
    ]
  },
  "_handle_auth_error": [
    "msg"
  ],
  "_authentication": [
    "request_fun"
  ],
  "_authority": [
    "scheme",
    "host",
    "port"
  ],
  "namespace": [
    "sharing",
    "owner",
    "app"
  ],
  "Context": {
    "__init__": [
      "self",
      "handler"
    ],
    "get_cookies": [
      "self"
    ],
    "has_cookies": [
      "self"
    ],
    "_auth_headers": [
      "self"
    ],
    "connect": [
      "self"
    ],
    "delete": [
      "self",
      "path_segment",
      "owner",
      "app",
      "sharing"
    ],
    "get": [
      "self",
      "path_segment",
      "owner",
      "app",
      "headers",
      "sharing"
    ],
    "post": [
      "self",
      "path_segment",
      "owner",
      "app",
      "sharing",
      "headers"
    ],
    "request": [
      "self",
      "path_segment",
      "method",
      "headers",
      "body",
      "owner",
      "app",
      "sharing"
    ],
    "login": [
      "self"
    ],
    "logout": [
      "self"
    ],
    "_abspath": [
      "self",
      "path_segment",
      "owner",
      "app",
      "sharing"
    ]
  },
  "connect": [],
  "HTTPError": {
    "__init__": [
      "self",
      "response",
      "_message"
    ]
  },
  "AuthenticationError": {
    "__init__": [
      "self",
      "message",
      "cause"
    ]
  },
  "_encode": [],
  "_spliturl": [
    "url"
  ],
  "HttpLib": {
    "__init__": [
      "self",
      "custom_handler",
      "verify",
      "key_file",
      "cert_file",
      "context",
      "retries",
      "retryDelay"
    ],
    "delete": [
      "self",
      "url",
      "headers"
    ],
    "get": [
      "self",
      "url",
      "headers"
    ],
    "post": [
      "self",
      "url",
      "headers"
    ],
    "request": [
      "self",
      "url",
      "message"
    ]
  },
  "ResponseReader": {
    "__init__": [
      "self",
      "response",
      "connection"
    ],
    "__str__": [
      "self"
    ],
    "empty": [
      "self"
    ],
    "peek": [
      "self",
      "size"
    ],
    "close": [
      "self"
    ],
    "read": [
      "self",
      "size"
    ],
    "readable": [
      "self"
    ],
    "readinto": [
      "self",
      "byte_array"
    ]
  },
  "handler": [
    "key_file",
    "cert_file",
    "timeout",
    "verify",
    "context"
  ],
  "Message": {
    "__init__": [
      "self",
      "type_",
      "message"
    ],
    "__repr__": [
      "self"
    ],
    "__eq__": [
      "self",
      "other"
    ],
    "__hash__": [
      "self"
    ]
  },
  "_ConcatenatedStream": {
    "__init__": [
      "self"
    ],
    "read": [
      "self",
      "n"
    ]
  },
  "_XMLDTDFilter": {
    "__init__": [
      "self",
      "stream"
    ],
    "read": [
      "self",
      "n"
    ]
  },
  "ResultsReader": {
    "__init__": [
      "self",
      "stream"
    ],
    "__iter__": [
      "self"
    ],
    "__next__": [
      "self"
    ],
    "_parse_results": [
      "self",
      "stream"
    ]
  },
  "JSONResultsReader": {
    "__init__": [
      "self",
      "stream"
    ],
    "__iter__": [
      "self"
    ],
    "__next__": [
      "self"
    ],
    "_parse_results": [
      "self",
      "stream"
    ]
  },
  "DEFAULT_LOG_FORMAT": [],
  "DEFAULT_DATE_FORMAT": [],
  "setup_logging": [
    "level",
    "log_format",
    "date_format"
  ],
  "__version_info__": [],
  "PATH_APPS": [],
  "PATH_CAPABILITIES": [],
  "PATH_CONF": [],
  "PATH_PROPERTIES": [],
  "PATH_DEPLOYMENT_CLIENTS": [],
  "PATH_DEPLOYMENT_TENANTS": [],
  "PATH_DEPLOYMENT_SERVERS": [],
  "PATH_DEPLOYMENT_SERVERCLASSES": [],
  "PATH_EVENT_TYPES": [],
  "PATH_FIRED_ALERTS": [],
  "PATH_INDEXES": [],
  "PATH_INPUTS": [],
  "PATH_JOBS": [],
  "PATH_JOBS_V2": [],
  "PATH_LOGGER": [],
  "PATH_MACROS": [],
  "PATH_MESSAGES": [],
  "PATH_MODULAR_INPUTS": [],
  "PATH_ROLES": [],
  "PATH_SAVED_SEARCHES": [],
  "PATH_STANZA": [],
  "PATH_USERS": [],
  "PATH_RECEIVERS_STREAM": [],
  "PATH_RECEIVERS_SIMPLE": [],
  "PATH_STORAGE_PASSWORDS": [],
  "XNAMEF_ATOM": [],
  "XNAME_ENTRY": [],
  "XNAME_CONTENT": [],
  "MATCH_ENTRY_CONTENT": [],
  "IllegalOperationException": {},
  "IncomparableException": {},
  "AmbiguousReferenceException": {},
  "InvalidNameException": {},
  "NoSuchCapability": {},
  "OperationError": {},
  "NotSupportedError": {},
  "_trailing": [
    "template"
  ],
  "_filter_content": [
    "content"
  ],
  "_path": [
    "base",
    "name"
  ],
  "_load_atom": [
    "response",
    "match"
  ],
  "_load_atom_entries": [
    "response"
  ],
  "_load_sid": [
    "response",
    "output_mode"
  ],
  "_parse_atom_entry": [
    "entry"
  ],
  "_parse_atom_metadata": [
    "content"
  ],
  "_BaseService": {},
  "Service": {
    "__init__": [
      "self"
    ],
    "apps": [
      "self"
    ],
    "confs": [
      "self"
    ],
    "capabilities": [
      "self"
    ],
    "event_types": [
      "self"
    ],
    "fired_alerts": [
      "self"
    ],
    "indexes": [
      "self"
    ],
    "info": [
      "self"
    ],
    "input": [
      "self",
      "path",
      "kind"
    ],
    "inputs": [
      "self"
    ],
    "job": [
      "self",
      "sid"
    ],
    "jobs": [
      "self"
    ],
    "loggers": [
      "self"
    ],
    "messages": [
      "self"
    ],
    "modular_input_kinds": [
      "self"
    ],
    "storage_passwords": [
      "self"
    ],
    "parse": [
      "self",
      "query"
    ],
    "restart": [
      "self",
      "timeout"
    ],
    "restart_required": [
      "self"
    ],
    "roles": [
      "self"
    ],
    "search": [
      "self",
      "query"
    ],
    "saved_searches": [
      "self"
    ],
    "macros": [
      "self"
    ],
    "settings": [
      "self"
    ],
    "splunk_version": [
      "self"
    ],
    "splunk_instance": [
      "self"
    ],
    "disable_v2_api": [
      "self"
    ],
    "kvstore_owner": [
      "self",
      "value"
    ],
    "kvstore": [
      "self"
    ],
    "users": [
      "self"
    ]
  },
  "Endpoint": {
    "__init__": [
      "self",
      "service",
      "path"
    ],
    "get_api_version": [
      "self",
      "path"
    ],
    "get": [
      "self",
      "path_segment",
      "owner",
      "app",
      "sharing"
    ],
    "post": [
      "self",
      "path_segment",
      "owner",
      "app",
      "sharing"
    ]
  },
  "Entity": {
    "defaults": [],
    "__init__": [
      "self",
      "service",
      "path"
    ],
    "__contains__": [
      "self",
      "item"
    ],
    "__eq__": [
      "self",
      "other"
    ],
    "__getattr__": [
      "self",
      "key"
    ],
    "__getitem__": [
      "self",
      "key"
    ],
    "_load_atom_entry": [
      "self",
      "response"
    ],
    "_load_state": [
      "self",
      "response"
    ],
    "_run_action": [
      "self",
      "path_segment"
    ],
    "_proper_namespace": [
      "self",
      "owner",
      "app",
      "sharing"
    ],
    "delete": [
      "self"
    ],
    "get": [
      "self",
      "path_segment",
      "owner",
      "app",
      "sharing"
    ],
    "post": [
      "self",
      "path_segment",
      "owner",
      "app",
      "sharing"
    ],
    "refresh": [
      "self",
      "state"
    ],
    "access": [
      "self"
    ],
    "content": [
      "self"
    ],
    "disable": [
      "self"
    ],
    "enable": [
      "self"
    ],
    "fields": [
      "self"
    ],
    "links": [
      "self"
    ],
    "name": [
      "self"
    ],
    "read": [
      "self",
      "response"
    ],
    "reload": [
      "self"
    ],
    "acl_update": [
      "self"
    ],
    "state": [
      "self"
    ],
    "update": [
      "self"
    ]
  },
  "ReadOnlyCollection": {
    "__init__": [
      "self",
      "service",
      "path",
      "item"
    ],
    "__contains__": [
      "self",
      "name"
    ],
    "__getitem__": [
      "self",
      "key"
    ],
    "__iter__": [
      "self"
    ],
    "__len__": [
      "self"
    ],
    "_entity_path": [
      "self",
      "state"
    ],
    "_load_list": [
      "self",
      "response"
    ],
    "itemmeta": [
      "self"
    ],
    "iter": [
      "self",
      "offset",
      "count",
      "pagesize"
    ],
    "list": [
      "self",
      "count"
    ]
  },
  "Collection": {
    "create": [
      "self",
      "name"
    ],
    "delete": [
      "self",
      "name"
    ],
    "get": [
      "self",
      "name",
      "owner",
      "app",
      "sharing"
    ]
  },
  "ConfigurationFile": {
    "__init__": [
      "self",
      "service",
      "path"
    ]
  },
  "Configurations": {
    "__init__": [
      "self",
      "service"
    ],
    "__getitem__": [
      "self",
      "key"
    ],
    "__contains__": [
      "self",
      "key"
    ],
    "create": [
      "self",
      "name"
    ],
    "delete": [
      "self",
      "key"
    ],
    "_entity_path": [
      "self",
      "state"
    ]
  },
  "Stanza": {
    "submit": [
      "self",
      "stanza"
    ],
    "__len__": [
      "self"
    ]
  },
  "StoragePassword": {
    "__init__": [
      "self",
      "service",
      "path"
    ],
    "clear_password": [
      "self"
    ],
    "encrypted_password": [
      "self"
    ],
    "realm": [
      "self"
    ],
    "username": [
      "self"
    ]
  },
  "StoragePasswords": {
    "__init__": [
      "self",
      "service"
    ],
    "create": [
      "self",
      "password",
      "username",
      "realm"
    ],
    "delete": [
      "self",
      "username",
      "realm"
    ]
  },
  "AlertGroup": {
    "__init__": [
      "self",
      "service",
      "path"
    ],
    "__len__": [
      "self"
    ],
    "alerts": [
      "self"
    ],
    "count": [
      "self"
    ]
  },
  "Indexes": {
    "get_default": [
      "self"
    ],
    "delete": [
      "self",
      "name"
    ]
  },
  "Index": {
    "__init__": [
      "self",
      "service",
      "path"
    ],
    "attach": [
      "self",
      "host",
      "source",
      "sourcetype"
    ],
    "attached_socket": [
      "self"
    ],
    "clean": [
      "self",
      "timeout"
    ],
    "roll_hot_buckets": [
      "self"
    ],
    "submit": [
      "self",
      "event",
      "host",
      "source",
      "sourcetype"
    ],
    "upload": [
      "self",
      "filename"
    ]
  },
  "Input": {
    "__init__": [
      "self",
      "service",
      "path",
      "kind"
    ],
    "update": [
      "self"
    ]
  },
  "Inputs": {
    "__init__": [
      "self",
      "service",
      "kindmap"
    ],
    "__getitem__": [
      "self",
      "key"
    ],
    "__contains__": [
      "self",
      "key"
    ],
    "create": [
      "self",
      "name",
      "kind"
    ],
    "delete": [
      "self",
      "name",
      "kind"
    ],
    "itemmeta": [
      "self",
      "kind"
    ],
    "_get_kind_list": [
      "self",
      "subpath"
    ],
    "kinds": [
      "self"
    ],
    "kindpath": [
      "self",
      "kind"
    ],
    "list": [
      "self"
    ],
    "__iter__": [
      "self"
    ],
    "iter": [
      "self"
    ],
    "oneshot": [
      "self",
      "path"
    ]
  },
  "Job": {
    "__init__": [
      "self",
      "service",
      "sid"
    ],
    "_load_atom_entry": [
      "self",
      "response"
    ],
    "cancel": [
      "self"
    ],
    "disable_preview": [
      "self"
    ],
    "enable_preview": [
      "self"
    ],
    "events": [
      "self"
    ],
    "finalize": [
      "self"
    ],
    "is_done": [
      "self"
    ],
    "is_ready": [
      "self"
    ],
    "name": [
      "self"
    ],
    "pause": [
      "self"
    ],
    "results": [
      "self"
    ],
    "preview": [
      "self"
    ],
    "searchlog": [
      "self"
    ],
    "set_priority": [
      "self",
      "value"
    ],
    "summary": [
      "self"
    ],
    "timeline": [
      "self"
    ],
    "touch": [
      "self"
    ],
    "set_ttl": [
      "self",
      "value"
    ],
    "unpause": [
      "self"
    ]
  },
  "Jobs": {
    "__init__": [
      "self",
      "service"
    ],
    "_load_list": [
      "self",
      "response"
    ],
    "create": [
      "self",
      "query"
    ],
    "export": [
      "self",
      "query"
    ],
    "itemmeta": [
      "self"
    ],
    "oneshot": [
      "self",
      "query"
    ]
  },
  "Loggers": {
    "__init__": [
      "self",
      "service"
    ],
    "itemmeta": [
      "self"
    ]
  },
  "ModularInputKind": {
    "__contains__": [
      "self",
      "name"
    ],
    "__getitem__": [
      "self",
      "name"
    ],
    "arguments": [
      "self"
    ],
    "update": [
      "self"
    ]
  },
  "SavedSearch": {
    "__init__": [
      "self",
      "service",
      "path"
    ],
    "acknowledge": [
      "self"
    ],
    "alert_count": [
      "self"
    ],
    "dispatch": [
      "self"
    ],
    "fired_alerts": [
      "self"
    ],
    "history": [
      "self"
    ],
    "update": [
      "self",
      "search"
    ],
    "scheduled_times": [
      "self",
      "earliest_time",
      "latest_time"
    ],
    "suppress": [
      "self",
      "expiration"
    ],
    "suppressed": [
      "self"
    ],
    "unsuppress": [
      "self"
    ]
  },
  "SavedSearches": {
    "__init__": [
      "self",
      "service"
    ],
    "create": [
      "self",
      "name",
      "search"
    ]
  },
  "Macro": {
    "__init__": [
      "self",
      "service",
      "path"
    ],
    "args": [
      "self"
    ],
    "definition": [
      "self"
    ],
    "errormsg": [
      "self"
    ],
    "iseval": [
      "self"
    ],
    "update": [
      "self",
      "definition"
    ],
    "validation": [
      "self"
    ]
  },
  "Macros": {
    "__init__": [
      "self",
      "service"
    ],
    "create": [
      "self",
      "name",
      "definition"
    ]
  },
  "Settings": {
    "__init__": [
      "self",
      "service"
    ],
    "update": [
      "self"
    ]
  },
  "User": {
    "role_entities": [
      "self"
    ]
  },
  "Users": {
    "__init__": [
      "self",
      "service"
    ],
    "__getitem__": [
      "self",
      "key"
    ],
    "__contains__": [
      "self",
      "name"
    ],
    "create": [
      "self",
      "username",
      "password",
      "roles"
    ],
    "delete": [
      "self",
      "name"
    ]
  },
  "Role": {
    "grant": [
      "self"
    ],
    "revoke": [
      "self"
    ]
  },
  "Roles": {
    "__init__": [
      "self",
      "service"
    ],
    "__getitem__": [
      "self",
      "key"
    ],
    "__contains__": [
      "self",
      "name"
    ],
    "create": [
      "self",
      "name"
    ],
    "delete": [
      "self",
      "name"
    ]
  },
  "Application": {
    "setupInfo": [
      "self"
    ],
    "package": [
      "self"
    ],
    "updateInfo": [
      "self"
    ]
  },
  "KVStoreCollections": {
    "__init__": [
      "self",
      "service"
    ],
    "__getitem__": [
      "self",
      "item"
    ],
    "create": [
      "self",
      "name",
      "accelerated_fields",
      "fields"
    ]
  },
  "KVStoreCollection": {
    "data": [
      "self"
    ],
    "update_accelerated_field": [
      "self",
      "name",
      "value"
    ],
    "update_field": [
      "self",
      "name",
      "value"
    ]
  },
  "KVStoreCollectionData": {
    "JSON_HEADER": [],
    "__init__": [
      "self",
      "collection"
    ],
    "_get": [
      "self",
      "url"
    ],
    "_post": [
      "self",
      "url"
    ],
    "_delete": [
      "self",
      "url"
    ],
    "query": [
      "self"
    ],
    "query_by_id": [
      "self",
      "id"
    ],
    "insert": [
      "self",
      "data"
    ],
    "delete": [
      "self",
      "query"
    ],
    "delete_by_id": [
      "self",
      "id"
    ],
    "update": [
      "self",
      "id",
      "data"
    ],
    "batch_find": [
      "self"
    ],
    "batch_save": [
      "self"
    ]
  },
  "LNAME_DICT": [],
  "LNAME_ITEM": [],
  "LNAME_KEY": [],
  "LNAME_LIST": [],
  "XNAMEF_REST": [],
  "XNAME_DICT": [],
  "XNAME_ITEM": [],
  "XNAME_KEY": [],
  "XNAME_LIST": [],
  "isdict": [
    "name"
  ],
  "isitem": [
    "name"
  ],
  "iskey": [
    "name"
  ],
  "islist": [
    "name"
  ],
  "hasattrs": [
    "element"
  ],
  "localname": [
    "xname"
  ],
  "load": [
    "text",
    "match"
  ],
  "load_attrs": [
    "element"
  ],
  "load_dict": [
    "element",
    "nametable"
  ],
  "load_elem": [
    "element",
    "nametable"
  ],
  "load_list": [
    "element",
    "nametable"
  ],
  "load_root": [
    "element",
    "nametable"
  ],
  "load_value": [
    "element",
    "nametable"
  ],
  "Record": {
    "sep": [],
    "__call__": [
      "self"
    ],
    "__getattr__": [
      "self",
      "name"
    ],
    "__delattr__": [
      "self",
      "name"
    ],
    "__setattr__": [
      "self",
      "name",
      "value"
    ],
    "fromkv": [
      "k",
      "v"
    ],
    "__getitem__": [
      "self",
      "key"
    ]
  },
  "record": [
    "value"
  ],
  "Script": {
    "__init__": [
      "self"
    ],
    "run": [
      "self",
      "args"
    ],
    "run_script": [
      "self",
      "args",
      "event_writer",
      "input_stream"
    ],
    "service": [
      "self"
    ],
    "get_scheme": [
      "self"
    ],
    "validate_input": [
      "self",
      "definition"
    ],
    "stream_events": [
      "self",
      "inputs",
      "ew"
    ]
  },
  "Scheme": {
    "streaming_mode_simple": [],
    "streaming_mode_xml": [],
    "__init__": [
      "self",
      "title"
    ],
    "add_argument": [
      "self",
      "arg"
    ],
    "to_xml": [
      "self"
    ]
  },
  "xml_compare": [
    "expected",
    "found"
  ],
  "parse_parameters": [
    "param_node"
  ],
  "parse_xml_data": [
    "parent_node",
    "child_node_tag"
  ],
  "Event": {
    "__init__": [
      "self",
      "data",
      "stanza",
      "time",
      "host",
      "index",
      "source",
      "sourcetype",
      "done",
      "unbroken"
    ],
    "write_to": [
      "self",
      "stream"
    ]
  },
  "EventWriter": {
    "DEBUG": [],
    "INFO": [],
    "WARN": [],
    "ERROR": [],
    "FATAL": [],
    "__init__": [
      "self",
      "output",
      "error"
    ],
    "write_event": [
      "self",
      "event"
    ],
    "log": [
      "self",
      "severity",
      "message"
    ],
    "log_exception": [
      "self",
      "message",
      "exception",
      "severity"
    ],
    "write_xml_document": [
      "self",
      "document"
    ],
    "close": [
      "self"
    ]
  },
  "InputDefinition": {
    "__init__": [
      "self"
    ],
    "__eq__": [
      "self",
      "other"
    ],
    "parse": [
      "stream"
    ]
  },
  "ValidationDefinition": {
    "__init__": [
      "self"
    ],
    "__eq__": [
      "self",
      "other"
    ],
    "parse": [
      "stream"
    ]
  },
  "Argument": {
    "data_type_boolean": [],
    "data_type_number": [],
    "data_type_string": [],
    "__init__": [
      "self",
      "name",
      "description",
      "validation",
      "data_type",
      "required_on_edit",
      "required_on_create",
      "title"
    ],
    "add_to_document": [
      "self",
      "parent"
    ]
  },
  "EventingCommand": {
    "transform": [
      "self",
      "records"
    ],
    "_execute": [
      "self",
      "ifile",
      "process"
    ]
  },
  "GeneratingCommand": {
    "generate": [
      "self"
    ],
    "_execute": [
      "self",
      "ifile",
      "process"
    ],
    "_execute_chunk_v2": [
      "self",
      "process",
      "chunk"
    ],
    "process": [
      "self",
      "argv",
      "ifile",
      "ofile",
      "allow_empty_input"
    ]
  },
  "ExternalSearchCommand": {
    "__init__": [
      "self",
      "path",
      "argv",
      "environ"
    ],
    "argv": [
      "self",
      "value"
    ],
    "environ": [
      "self",
      "value"
    ],
    "logger": [
      "self"
    ],
    "path": [
      "self"
    ],
    "execute": [
      "self"
    ]
  },
  "execute": [
    "path",
    "argv",
    "environ",
    "command_class"
  ],
  "StreamingCommand": {
    "stream": [
      "self",
      "records"
    ],
    "_execute": [
      "self",
      "ifile",
      "process"
    ]
  },
  "set_binary_mode": [
    "fh"
  ],
  "CommandLineParser": {
    "parse": [
      "cls",
      "command",
      "argv"
    ],
    "unquote": [
      "cls",
      "string"
    ],
    "_arguments_re": [],
    "_escaped_character_re": [],
    "_fieldnames_re": [],
    "_options_re": []
  },
  "ConfigurationSettingsType": {
    "__new__": [
      "mcs",
      "module",
      "name",
      "bases"
    ],
    "__init__": [
      "cls",
      "module",
      "name",
      "bases"
    ],
    "validate_configuration_setting": [
      "specification",
      "name",
      "value"
    ],
    "specification": [],
    "specification_matrix": []
  },
  "CsvDialect": {
    "delimiter": [],
    "quotechar": [],
    "doublequote": [],
    "skipinitialspace": [],
    "lineterminator": [],
    "quoting": []
  },
  "InputHeader": {
    "__str__": [
      "self"
    ],
    "read": [
      "self",
      "ifile"
    ]
  },
  "MetadataDecoder": {
    "__init__": [
      "self"
    ],
    "_object_hook": [
      "dictionary"
    ]
  },
  "MetadataEncoder": {
    "__init__": [
      "self"
    ],
    "default": [
      "self",
      "o"
    ],
    "_separators": []
  },
  "ObjectView": {
    "__init__": [
      "self",
      "dictionary"
    ],
    "update": [
      "self",
      "obj"
    ],
    "__repr__": [
      "self"
    ],
    "__str__": [
      "self"
    ]
  },
  "Recorder": {
    "__init__": [
      "self",
      "path",
      "f"
    ],
    "__getattr__": [
      "self",
      "name"
    ],
    "__iter__": [
      "self"
    ],
    "read": [
      "self",
      "size"
    ],
    "readline": [
      "self",
      "size"
    ],
    "record": [
      "self"
    ],
    "write": [
      "self",
      "text"
    ]
  },
  "RecordWriter": {
    "__init__": [
      "self",
      "ofile",
      "maxresultrows"
    ],
    "is_flushed": [
      "self",
      "value"
    ],
    "ofile": [
      "self",
      "value"
    ],
    "pending_record_count": [
      "self"
    ],
    "_record_count": [
      "self"
    ],
    "committed_record_count": [
      "self"
    ],
    "_total_record_count": [
      "self"
    ],
    "write": [
      "self",
      "data"
    ],
    "flush": [
      "self",
      "finished",
      "partial"
    ],
    "write_message": [
      "self",
      "message_type",
      "message_text"
    ],
    "write_record": [
      "self",
      "record"
    ],
    "write_records": [
      "self",
      "records"
    ],
    "_clear": [
      "self"
    ],
    "_ensure_validity": [
      "self"
    ],
    "_write_record": [
      "self",
      "record"
    ]
  },
  "RecordWriterV1": {
    "flush": [
      "self",
      "finished",
      "partial"
    ],
    "_message_level": []
  },
  "RecordWriterV2": {
    "flush": [
      "self",
      "finished",
      "partial"
    ],
    "write_chunk": [
      "self",
      "finished"
    ],
    "write_metadata": [
      "self",
      "configuration"
    ],
    "write_metric": [
      "self",
      "name",
      "value"
    ],
    "_clear": [
      "self"
    ],
    "_write_chunk": [
      "self",
      "metadata",
      "body"
    ]
  },
  "ReportingCommand": {
    "__init__": [
      "self"
    ],
    "phase": [],
    "map": [
      "self",
      "records"
    ],
    "_has_custom_method": [
      "self",
      "method_name"
    ],
    "prepare": [
      "self"
    ],
    "reduce": [
      "self",
      "records"
    ],
    "_execute": [
      "self",
      "ifile",
      "process"
    ]
  },
  "Configuration": {
    "__init__": [
      "self",
      "o"
    ],
    "__call__": [
      "self",
      "o"
    ]
  },
  "ConfigurationSetting": {
    "__init__": [
      "self",
      "fget",
      "fset",
      "fdel",
      "doc",
      "name",
      "readonly",
      "value"
    ],
    "__call__": [
      "self",
      "function"
    ],
    "deleter": [
      "self",
      "function"
    ],
    "getter": [
      "self",
      "function"
    ],
    "setter": [
      "self",
      "function"
    ],
    "fix_up": [
      "cls",
      "values"
    ],
    "_copy_extra_attributes": [
      "self",
      "other"
    ],
    "_get_specification": [
      "self"
    ]
  },
  "Option": {
    "__init__": [
      "self",
      "fget",
      "fset",
      "fdel",
      "doc",
      "name",
      "default",
      "require",
      "validate"
    ],
    "__call__": [
      "self",
      "function"
    ],
    "deleter": [
      "self",
      "function"
    ],
    "getter": [
      "self",
      "function"
    ],
    "setter": [
      "self",
      "function"
    ],
    "fix_up": [
      "cls",
      "command_class"
    ],
    "_copy_extra_attributes": [
      "self",
      "other"
    ]
  },
  "configure_logging": [
    "logger_name",
    "filename"
  ],
  "_current_logging_configuration_file": [],
  "splunk_home": [],
  "app_file": [],
  "app_root": [],
  "Validator": {
    "__call__": [
      "self",
      "value"
    ],
    "format": [
      "self",
      "value"
    ]
  },
  "Boolean": {
    "truth_values": [],
    "__call__": [
      "self",
      "value"
    ],
    "format": [
      "self",
      "value"
    ]
  },
  "Code": {
    "__init__": [
      "self",
      "mode"
    ],
    "__call__": [
      "self",
      "value"
    ],
    "format": [
      "self",
      "value"
    ],
    "object": []
  },
  "Fieldname": {
    "pattern": [],
    "__call__": [
      "self",
      "value"
    ],
    "format": [
      "self",
      "value"
    ]
  },
  "File": {
    "__init__": [
      "self",
      "mode",
      "buffering",
      "directory"
    ],
    "__call__": [
      "self",
      "value"
    ],
    "format": [
      "self",
      "value"
    ],
    "_var_run_splunk": []
  },
  "Integer": {
    "__init__": [
      "self",
      "minimum",
      "maximum"
    ],
    "__call__": [
      "self",
      "value"
    ],
    "format": [
      "self",
      "value"
    ]
  },
  "Float": {
    "__init__": [
      "self",
      "minimum",
      "maximum"
    ],
    "__call__": [
      "self",
      "value"
    ],
    "format": [
      "self",
      "value"
    ]
  },
  "Duration": {
    "__call__": [
      "self",
      "value"
    ],
    "format": [
      "self",
      "value"
    ],
    "_60": [],
    "_unsigned": []
  },
  "List": {
    "__init__": [
      "self",
      "validator"
    ],
    "__call__": [
      "self",
      "value"
    ],
    "format": [
      "self",
      "value"
    ]
  },
  "Map": {
    "__init__": [
      "self"
    ],
    "__call__": [
      "self",
      "value"
    ],
    "format": [
      "self",
      "value"
    ]
  },
  "Match": {
    "__init__": [
      "self",
      "name",
      "pattern",
      "flags"
    ],
    "__call__": [
      "self",
      "value"
    ],
    "format": [
      "self",
      "value"
    ]
  },
  "OptionName": {
    "pattern": [],
    "__call__": [
      "self",
      "value"
    ],
    "format": [
      "self",
      "value"
    ]
  },
  "RegularExpression": {
    "__call__": [
      "self",
      "value"
    ],
    "format": [
      "self",
      "value"
    ]
  },
  "Set": {
    "__init__": [
      "self"
    ],
    "__call__": [
      "self",
      "value"
    ],
    "format": [
      "self",
      "value"
    ]
  },
  "SearchCommand": {
    "__init__": [
      "self"
    ],
    "__str__": [
      "self"
    ],
    "logging_configuration": [
      "self",
      "value"
    ],
    "logging_level": [
      "self",
      "value"
    ],
    "add_field": [
      "self",
      "current_record",
      "field_name",
      "field_value"
    ],
    "gen_record": [
      "self"
    ],
    "record": [],
    "show_configuration": [],
    "configuration": [
      "self"
    ],
    "fieldnames": [
      "self",
      "value"
    ],
    "input_header": [
      "self"
    ],
    "logger": [
      "self"
    ],
    "metadata": [
      "self"
    ],
    "options": [
      "self"
    ],
    "protocol_version": [
      "self"
    ],
    "search_results_info": [
      "self"
    ],
    "service": [
      "self"
    ],
    "error_exit": [
      "self",
      "error",
      "message"
    ],
    "finish": [
      "self"
    ],
    "flush": [
      "self"
    ],
    "prepare": [
      "self"
    ],
    "process": [
      "self",
      "argv",
      "ifile",
      "ofile",
      "allow_empty_input"
    ],
    "_map_input_header": [
      "self"
    ],
    "_map_metadata": [
      "self",
      "argv"
    ],
    "_metadata_map": [],
    "_MetadataSource": [],
    "_prepare_protocol_v1": [
      "self",
      "argv",
      "ifile",
      "ofile"
    ],
    "_prepare_recording": [
      "self",
      "argv",
      "ifile",
      "ofile"
    ],
    "_process_protocol_v1": [
      "self",
      "argv",
      "ifile",
      "ofile"
    ],
    "_protocol_v2_option_parser": [
      "self",
      "arg"
    ],
    "_process_protocol_v2": [
      "self",
      "argv",
      "ifile",
      "ofile"
    ],
    "write_debug": [
      "self",
      "message"
    ],
    "write_error": [
      "self",
      "message"
    ],
    "write_fatal": [
      "self",
      "message"
    ],
    "write_info": [
      "self",
      "message"
    ],
    "write_warning": [
      "self",
      "message"
    ],
    "write_metric": [
      "self",
      "name",
      "value"
    ],
    "_decode_list": [
      "mv"
    ],
    "_encoded_value": [],
    "_execute": [
      "self",
      "ifile",
      "process"
    ],
    "_as_binary_stream": [
      "ifile"
    ],
    "_read_chunk": [
      "istream"
    ],
    "_header": [],
    "_records_protocol_v1": [
      "self",
      "ifile"
    ],
    "_read_csv_records": [
      "self",
      "ifile"
    ],
    "_execute_v2": [
      "self",
      "ifile",
      "process"
    ],
    "_execute_chunk_v2": [
      "self",
      "process",
      "chunk"
    ],
    "_report_unexpected_error": [
      "self"
    ]
  },
  "SearchMetric": [],
  "dispatch": [
    "command_class",
    "argv",
    "input_file",
    "output_file",
    "module_name",
    "allow_empty_input"
  ]
}